InterPhon/__init__.py
InterPhon/interphon.py
InterPhon/analysis/__init__.py
InterPhon/analysis/band.py
InterPhon/analysis/dos.py
InterPhon/analysis/mode.py
InterPhon/analysis/thermal_properties.py
InterPhon/core/__init__.py
InterPhon/core/post_check.py
InterPhon/core/post_process.py
InterPhon/core/pre_check.py
InterPhon/core/pre_process.py
InterPhon/core/super_cell.py
InterPhon/core/unit_cell.py
InterPhon/error/__init__.py
InterPhon/error/error.py
InterPhon/inout/__init__.py
InterPhon/inout/aims.py
InterPhon/inout/espresso.py
InterPhon/inout/vasp.py
InterPhon/util/__init__.py
InterPhon/util/atomic_weight.py
InterPhon/util/k_points.py
InterPhon/util/linear_tetrahedron_method.py
InterPhon/util/symmetry.py
InterPhon/util/typing.py
InterPhon-1.5.0.dist-info/LICENSE
InterPhon-1.5.0.dist-info/METADATA
InterPhon-1.5.0.dist-info/WHEEL
InterPhon-1.5.0.dist-info/entry_points.txt
InterPhon-1.5.0.dist-info/top_level.txt
InterPhon-1.5.0.dist-info/RECORD
