Metadata-Version: 2.1
Name: InterPhon
Version: 1.5.0
Summary: A Python Package for Ab initio Interface Phonon Calculations within a 3D Electronic Structure Framework
Home-page: https://github.com/inwonyeu/interphon
Author: In Won Yeu
Author-email: yiw0121@snu.ac.kr
License: LGPLv2.1
Platform: UNKNOWN
Requires-Python: >=3
License-File: LICENSE
Requires-Dist: Click
Requires-Dist: numpy
Requires-Dist: matplotlib
Requires-Dist: PyYAML
